not_given/__init__.py
notgiven/__init__.py
notgiven-0.0.5.dist-info/METADATA
notgiven-0.0.5.dist-info/WHEEL
notgiven-0.0.5.dist-info/licenses/LICENSE
notgiven-0.0.5.dist-info/RECORD
